helloworld/__init__.py
helloworld/_info.py
helloworld_mkmenta-0.0.4.dist-info/LICENSE.txt
helloworld_mkmenta-0.0.4.dist-info/METADATA
helloworld_mkmenta-0.0.4.dist-info/WHEEL
helloworld_mkmenta-0.0.4.dist-info/top_level.txt
helloworld_mkmenta-0.0.4.dist-info/RECORD
