Metadata-Version: 2.1
Name: helloworld-mkmenta
Version: 0.0.4
Summary: Say hello!
Home-page: https://github.com/mkmenta/python-package-example
Author: Mikel Menta Garde
Author-email: thisisnotmyemail@gmail.com
License: UNKNOWN
Platform: UNKNOWN
Classifier: Programming Language :: Python :: 3 :: Only
Classifier: Programming Language :: Python :: 3.9
Classifier: License :: OSI Approved :: MIT License
Classifier: Operating System :: OS Independent
Requires-Dist: termcolor (>=1.1.0)
Provides-Extra: dev
Requires-Dist: pytest ; extra == 'dev'
Requires-Dist: pydocstyle ; extra == 'dev'
Requires-Dist: pycodestyle ; extra == 'dev'
